archi/__init__.py
archi/broker.py
archi/consumer.py
archi/emitter.py
archi/event.py
pooter-0.4.4.dist-info/licenses/LICENSE.txt
pooter-0.4.4.dist-info/METADATA
pooter-0.4.4.dist-info/WHEEL
pooter-0.4.4.dist-info/top_level.txt
pooter-0.4.4.dist-info/RECORD
