Metadata-Version: 2.4
Name: pooter
Version: 0.4.4
Summary: Async coordination system using Broker-Emitter-Consumer with testing, we simply call it: "Event Architecture based on Promises"
Author-email: Lê Cường <cuongdayne17@gmail.com>
License: MIT
Keywords: broker,emitter,eventbus,async,coordination,fastapi,promise,architecture
Classifier: Development Status :: 3 - Alpha
Classifier: Programming Language :: Python :: 3
Classifier: Programming Language :: Python :: 3.11
Classifier: License :: OSI Approved :: MIT License
Classifier: Operating System :: OS Independent
Classifier: Framework :: AsyncIO
Classifier: Intended Audience :: Developers
Classifier: Topic :: Software Development :: Libraries :: Application Frameworks
Requires-Python: >=3.11
License-File: LICENSE.txt
Requires-Dist: colorama==0.4.6
Requires-Dist: iniconfig==2.1.0
Requires-Dist: packaging==25.0
Requires-Dist: pluggy==1.6.0
Requires-Dist: Pygments==2.19.1
Requires-Dist: pytest==8.4.0
Requires-Dist: pytest-asyncio==1.0.0
Requires-Dist: uuid6==2025.0.0
Provides-Extra: dev
Requires-Dist: black>=23.0; extra == "dev"
Requires-Dist: ruff>=0.3.0; extra == "dev"
Requires-Dist: mypy>=1.8.0; extra == "dev"
Dynamic: license-file
